{"links": {"self": {"href": "data/repositories/osrf/gzweb/issues/89/comments/37516571.json"}, "html": {"href": "#!/osrf/gzweb/issues/89#comment-37516571"}}, "issue": {"links": {"self": {"href": "data/repositories/osrf/gzweb/issues/89.json"}}, "type": "issue", "id": 89, "repository": {"links": {"self": {"href": "data/repositories/osrf/gzweb.json"}, "html": {"href": "#!/osrf/gzweb"}, "avatar": {"href": "data/bytebucket.org/ravatar/{3e2fc3f2-dc25-453b-9792-943c743d9b40}ts=1609263"}}, "type": "repository", "name": "gzweb", "full_name": "osrf/gzweb", "uuid": "{3e2fc3f2-dc25-453b-9792-943c743d9b40}"}, "title": "roslaunch: [gazebo-2] process has died [pid 7605, exit code 139"}, "content": {"raw": "I am so sorry, I totally screwed up here. \nThis should not be in Gzweb, but in Gazebo. Can someone please move this there?", "markup": "markdown", "html": "<p>I am so sorry, I totally screwed up here. \nThis should not be in Gzweb, but in Gazebo. Can someone please move this there?</p>", "type": "rendered"}, "created_on": "2017-06-12T05:46:19.640353+00:00", "user": {"display_name": "Philipp Benz", "uuid": "{35fe857e-fca7-4739-b5fa-9846401a5616}", "links": {"self": {"href": "https://api.bitbucket.org/2.0/users/%7B35fe857e-fca7-4739-b5fa-9846401a5616%7D"}, "html": {"href": "https://bitbucket.org/%7B35fe857e-fca7-4739-b5fa-9846401a5616%7D/"}, "avatar": {"href": "data/secure.gravatar.com/avatar/a414264f953a8af3742e3891b377eea6d=httpsavatar-management--avatars.us-west-2.prod.public.atl-paas.netinitialsPB-6.png"}}, "nickname": "Kaonashi2", "type": "user", "account_id": "557058:abdfd77a-91cf-486b-8c05-92c67fef178b"}, "updated_on": null, "type": "issue_comment", "id": 37516571}