{"links": {"self": {"href": "data/repositories/osrf/gzweb/pullrequests/22/comments/1601431.json"}, "html": {"href": "#!/osrf/gzweb/pull-requests/22/_/diff#comment-1601431"}}, "deleted": false, "pullrequest": {"type": "pullrequest", "id": 22, "links": {"self": {"href": "data/repositories/osrf/gzweb/pullrequests/22.json"}, "html": {"href": "#!/osrf/gzweb/pull-requests/22"}}, "title": "Update deploy process"}, "content": {"raw": "* The models seem to be working fine. Much more organized now :)\n* I think I've always run `deploy.sh` without `sudo`\n* Can't say anything about osx ;)", "markup": "markdown", "html": "<ul>\n<li>The models seem to be working fine. Much more organized now :)</li>\n<li>I think I've always run <code>deploy.sh</code> without <code>sudo</code></li>\n<li>Can't say anything about osx ;)</li>\n</ul>", "type": "rendered"}, "created_on": "2014-04-07T20:21:20.447432+00:00", "user": {"display_name": "Louise Poubel", "uuid": "{5cfa2075-477b-4ded-bdb9-8d2479544ec4}", "links": {"self": {"href": "https://api.bitbucket.org/2.0/users/%7B5cfa2075-477b-4ded-bdb9-8d2479544ec4%7D"}, "html": {"href": "https://bitbucket.org/%7B5cfa2075-477b-4ded-bdb9-8d2479544ec4%7D/"}, "avatar": {"href": "https://avatar-management--avatars.us-west-2.prod.public.atl-paas.net/557058:6ff86fcb-b7ab-44a5-b8a6-f6d9cae8b6e8/7d903d90-c5ea-4182-b7ef-0d467e9e1c74/128"}}, "nickname": "chapulina", "type": "user", "account_id": "557058:6ff86fcb-b7ab-44a5-b8a6-f6d9cae8b6e8"}, "updated_on": "2014-04-07T20:21:20.630913+00:00", "type": "pullrequest_comment", "id": 1601431}