{"links": {"self": {"href": "data/repositories/osrf/gzweb/pullrequests/9/comments/997510.json"}, "html": {"href": "#!/osrf/gzweb/pull-requests/9/_/diff#comment-997510"}}, "deleted": false, "pullrequest": {"type": "pullrequest", "id": 9, "links": {"self": {"href": "data/repositories/osrf/gzweb/pullrequests/9.json"}, "html": {"href": "#!/osrf/gzweb/pull-requests/9"}}, "title": "Increase icon image contrast"}, "content": {"raw": "Oh, like this maybe: [.ai file](https://www.dropbox.com/s/85bkcw2ci9j1v5k/rotate.ai) and [.png ](https://www.dropbox.com/s/2eosiuv15c2ej2y/rotate.png)", "markup": "markdown", "html": "<p>Oh, like this maybe: <a data-is-external-link=\"true\" href=\"https://www.dropbox.com/s/85bkcw2ci9j1v5k/rotate.ai\" rel=\"nofollow\">.ai file</a> and <a data-is-external-link=\"true\" href=\"https://www.dropbox.com/s/2eosiuv15c2ej2y/rotate.png\" rel=\"nofollow\">.png </a></p>", "type": "rendered"}, "created_on": "2013-12-27T22:44:23.167556+00:00", "user": {"display_name": "Steffi Paepcke", "uuid": "{88ec2edf-5653-4e93-b139-6f2418d9fde5}", "links": {"self": {"href": "https://api.bitbucket.org/2.0/users/%7B88ec2edf-5653-4e93-b139-6f2418d9fde5%7D"}, "html": {"href": "https://bitbucket.org/%7B88ec2edf-5653-4e93-b139-6f2418d9fde5%7D/"}, "avatar": {"href": "https://bitbucket.org/account/spaepcke/avatar/"}}, "nickname": "spaepcke", "type": "user", "account_id": null}, "updated_on": "2013-12-27T22:44:23.174776+00:00", "type": "pullrequest_comment", "id": 997510}