{"pagelen": 100, "values": [{"links": {"self": {"href": "data/repositories/osrf/gzweb/issues/4/comments/6182005.json"}, "html": {"href": "#!/osrf/gzweb/issues/4#comment-6182005"}}, "issue": {"links": {"self": {"href": "data/repositories/osrf/gzweb/issues/4.json"}}, "type": "issue", "id": 4, "repository": {"links": {"self": {"href": "data/repositories/osrf/gzweb.json"}, "html": {"href": "#!/osrf/gzweb"}, "avatar": {"href": "data/bytebucket.org/ravatar/{3e2fc3f2-dc25-453b-9792-943c743d9b40}ts=1609263"}}, "type": "repository", "name": "gzweb", "full_name": "osrf/gzweb", "uuid": "{3e2fc3f2-dc25-453b-9792-943c743d9b40}"}, "title": "Missing terrain"}, "content": {"raw": null, "markup": "markdown", "html": "", "type": "rendered"}, "created_on": "2013-09-24T06:05:32.385731+00:00", "user": {"display_name": "Ian Chen", "uuid": "{eaa6fca5-6deb-43f6-907f-971c144735dd}", "links": {"self": {"href": "https://api.bitbucket.org/2.0/users/%7Beaa6fca5-6deb-43f6-907f-971c144735dd%7D"}, "html": {"href": "https://bitbucket.org/%7Beaa6fca5-6deb-43f6-907f-971c144735dd%7D/"}, "avatar": {"href": "https://avatar-management--avatars.us-west-2.prod.public.atl-paas.net/557058:10b01d41-a2e9-4a41-a907-e6e2f03b6cd5/1e4adcdf-1946-4280-9aea-eb5f15a7f912/128"}}, "nickname": "Ian Chen", "type": "user", "account_id": "557058:10b01d41-a2e9-4a41-a907-e6e2f03b6cd5"}, "updated_on": null, "type": "issue_comment", "id": 6182005}, {"links": {"self": {"href": "data/repositories/osrf/gzweb/issues/4/comments/6528883.json"}, "html": {"href": "#!/osrf/gzweb/issues/4#comment-6528883"}}, "issue": {"links": {"self": {"href": "data/repositories/osrf/gzweb/issues/4.json"}}, "type": "issue", "id": 4, "repository": {"links": {"self": {"href": "data/repositories/osrf/gzweb.json"}, "html": {"href": "#!/osrf/gzweb"}, "avatar": {"href": "data/bytebucket.org/ravatar/{3e2fc3f2-dc25-453b-9792-943c743d9b40}ts=1609263"}}, "type": "repository", "name": "gzweb", "full_name": "osrf/gzweb", "uuid": "{3e2fc3f2-dc25-453b-9792-943c743d9b40}"}, "title": "Missing terrain"}, "content": {"raw": "c5a1794 : basic terrain\n\n70a5eb8 : texture blending\n\n23f5dea :  directional lighting\n\n", "markup": "markdown", "html": "<p><a href=\"#!/osrf/gzweb/commits/c5a1794\" rel=\"nofollow\" class=\"ap-connect-link\">c5a1794</a> : basic terrain</p>\n<p><a href=\"#!/osrf/gzweb/commits/70a5eb8\" rel=\"nofollow\" class=\"ap-connect-link\">70a5eb8</a> : texture blending</p>\n<p><a href=\"#!/osrf/gzweb/commits/23f5dea\" rel=\"nofollow\" class=\"ap-connect-link\">23f5dea</a> :  directional lighting</p>", "type": "rendered"}, "created_on": "2013-10-19T01:33:28.283499+00:00", "user": {"display_name": "Ian Chen", "uuid": "{eaa6fca5-6deb-43f6-907f-971c144735dd}", "links": {"self": {"href": "https://api.bitbucket.org/2.0/users/%7Beaa6fca5-6deb-43f6-907f-971c144735dd%7D"}, "html": {"href": "https://bitbucket.org/%7Beaa6fca5-6deb-43f6-907f-971c144735dd%7D/"}, "avatar": {"href": "https://avatar-management--avatars.us-west-2.prod.public.atl-paas.net/557058:10b01d41-a2e9-4a41-a907-e6e2f03b6cd5/1e4adcdf-1946-4280-9aea-eb5f15a7f912/128"}}, "nickname": "Ian Chen", "type": "user", "account_id": "557058:10b01d41-a2e9-4a41-a907-e6e2f03b6cd5"}, "updated_on": "2013-10-22T00:05:16.909178+00:00", "type": "issue_comment", "id": 6528883}, {"links": {"self": {"href": "data/repositories/osrf/gzweb/issues/4/comments/6559268.json"}, "html": {"href": "#!/osrf/gzweb/issues/4#comment-6559268"}}, "issue": {"links": {"self": {"href": "data/repositories/osrf/gzweb/issues/4.json"}}, "type": "issue", "id": 4, "repository": {"links": {"self": {"href": "data/repositories/osrf/gzweb.json"}, "html": {"href": "#!/osrf/gzweb"}, "avatar": {"href": "data/bytebucket.org/ravatar/{3e2fc3f2-dc25-453b-9792-943c743d9b40}ts=1609263"}}, "type": "repository", "name": "gzweb", "full_name": "osrf/gzweb", "uuid": "{3e2fc3f2-dc25-453b-9792-943c743d9b40}"}, "title": "Missing terrain"}, "content": {"raw": null, "markup": "markdown", "html": "", "type": "rendered"}, "created_on": "2013-10-22T00:05:20.196577+00:00", "user": {"display_name": "Ian Chen", "uuid": "{eaa6fca5-6deb-43f6-907f-971c144735dd}", "links": {"self": {"href": "https://api.bitbucket.org/2.0/users/%7Beaa6fca5-6deb-43f6-907f-971c144735dd%7D"}, "html": {"href": "https://bitbucket.org/%7Beaa6fca5-6deb-43f6-907f-971c144735dd%7D/"}, "avatar": {"href": "https://avatar-management--avatars.us-west-2.prod.public.atl-paas.net/557058:10b01d41-a2e9-4a41-a907-e6e2f03b6cd5/1e4adcdf-1946-4280-9aea-eb5f15a7f912/128"}}, "nickname": "Ian Chen", "type": "user", "account_id": "557058:10b01d41-a2e9-4a41-a907-e6e2f03b6cd5"}, "updated_on": null, "type": "issue_comment", "id": 6559268}], "page": 1, "size": 3}